hdf5_zcl/__init__.cpython-310-x86_64-linux-gnu.so
hdf5_zcl/hdf5_function.cpython-310-x86_64-linux-gnu.so
hdf5_zcl/swmr/library/Bufferlib.cpython-310-x86_64-linux-gnu.so
hdf5_zcl/swmr/library/__init__.cpython-310-x86_64-linux-gnu.so
hdf5_zcl/swmr/library/swmr_writer.cpython-310-x86_64-linux-gnu.so
hdf5_zcl/swmr/library/swmrlib.cpython-310-x86_64-linux-gnu.so
hdf5_zcl-1.1.2.2024.9.28.23.21.dist-info/METADATA
hdf5_zcl-1.1.2.2024.9.28.23.21.dist-info/WHEEL
hdf5_zcl-1.1.2.2024.9.28.23.21.dist-info/top_level.txt
hdf5_zcl-1.1.2.2024.9.28.23.21.dist-info/RECORD
