Metadata-Version: 2.1
Name: hdf5_zcl
Version: 1.1.2.2024.9.28.23.21
Summary: hdf5 library
Author: zhangchenglong
Author-email: zhangchl@ihep.ac.cn
License: Mozilla Public License 2.0
